google/apps/meet/__init__.py
google/apps/meet/gapic_version.py
google/apps/meet/py.typed
google/apps/meet_v2/__init__.py
google/apps/meet_v2/gapic_metadata.json
google/apps/meet_v2/gapic_version.py
google/apps/meet_v2/py.typed
google/apps/meet_v2/services/__init__.py
google/apps/meet_v2/services/conference_records_service/__init__.py
google/apps/meet_v2/services/conference_records_service/async_client.py
google/apps/meet_v2/services/conference_records_service/client.py
google/apps/meet_v2/services/conference_records_service/pagers.py
google/apps/meet_v2/services/conference_records_service/transports/__init__.py
google/apps/meet_v2/services/conference_records_service/transports/base.py
google/apps/meet_v2/services/conference_records_service/transports/grpc.py
google/apps/meet_v2/services/conference_records_service/transports/grpc_asyncio.py
google/apps/meet_v2/services/conference_records_service/transports/rest.py
google/apps/meet_v2/services/conference_records_service/transports/rest_base.py
google/apps/meet_v2/services/spaces_service/__init__.py
google/apps/meet_v2/services/spaces_service/async_client.py
google/apps/meet_v2/services/spaces_service/client.py
google/apps/meet_v2/services/spaces_service/transports/__init__.py
google/apps/meet_v2/services/spaces_service/transports/base.py
google/apps/meet_v2/services/spaces_service/transports/grpc.py
google/apps/meet_v2/services/spaces_service/transports/grpc_asyncio.py
google/apps/meet_v2/services/spaces_service/transports/rest.py
google/apps/meet_v2/services/spaces_service/transports/rest_base.py
google/apps/meet_v2/types/__init__.py
google/apps/meet_v2/types/resource.py
google/apps/meet_v2/types/service.py
google/apps/meet_v2beta/__init__.py
google/apps/meet_v2beta/gapic_metadata.json
google/apps/meet_v2beta/gapic_version.py
google/apps/meet_v2beta/py.typed
google/apps/meet_v2beta/services/__init__.py
google/apps/meet_v2beta/services/conference_records_service/__init__.py
google_apps_meet-0.3.0.dist-info/licenses/LICENSE
google_apps_meet-0.3.0.dist-info/METADATA
google_apps_meet-0.3.0.dist-info/WHEEL
google_apps_meet-0.3.0.dist-info/top_level.txt
google_apps_meet-0.3.0.dist-info/RECORD
